MANIFEST.in
board_hr_holidays_view.xml
hr_bel_holidays_2008.xml
hr_holidays_data.xml
hr_holidays_demo.xml
hr_holidays_report.xml
hr_holidays_view.xml
hr_holidays_workflow.xml
setup.py
./__init__.py
./__openerp__.py
./hr_holidays.py
./report/__init__.py
./report/available_holidays.py
./report/holidays_summary_report.py
./report/hr_holidays_report.py
./wizard/__init__.py
./wizard/hr_holidays_summary_department.py
./wizard/hr_holidays_summary_employees.py
i18n/am.po
i18n/ar.po
i18n/bg.po
i18n/bs.po
i18n/ca.po
i18n/cs.po
i18n/da.po
i18n/de.po
i18n/el.po
i18n/es.po
i18n/es_AR.po
i18n/es_CR.po
i18n/es_EC.po
i18n/es_MX.po
i18n/es_VE.po
i18n/et.po
i18n/fi.po
i18n/fr.po
i18n/gu.po
i18n/hi.po
i18n/hr.po
i18n/hr_holidays.pot
i18n/hu.po
i18n/id.po
i18n/it.po
i18n/ja.po
i18n/ko.po
i18n/lt.po
i18n/lv.po
i18n/mk.po
i18n/mn.po
i18n/nb.po
i18n/nl.po
i18n/nl_BE.po
i18n/pl.po
i18n/pt.po
i18n/pt_BR.po
i18n/ro.po
i18n/ru.po
i18n/sl.po
i18n/sq.po
i18n/sr.po
i18n/sr@latin.po
i18n/sv.po
i18n/th.po
i18n/th_TH.po
i18n/tlh.po
i18n/tr.po
i18n/uk.po
i18n/vi.po
i18n/zh_CN.po
i18n/zh_TW.po
images/hr_allocation_requests.jpeg
images/hr_leave_requests.jpeg
images/leaves_analysis.jpeg
openerp_hr_holidays.egg-info/PKG-INFO
openerp_hr_holidays.egg-info/SOURCES.txt
openerp_hr_holidays.egg-info/dependency_links.txt
openerp_hr_holidays.egg-info/requires.txt
openerp_hr_holidays.egg-info/top_level.txt
process/hr_holidays_process.xml
report/available_holidays_view.xml
report/holidays_summary.xsl
report/hr_custom_default.xsl
report/hr_custom_rml.xsl
report/hr_holidays_report_view.xml
security/ir.model.access.csv
security/ir_rule.xml
static/src/img/icon.png
test/hr_holidays_report.yml
test/test_hr_holiday.yml
wizard/hr_holidays_summary_department_view.xml
wizard/hr_holidays_summary_employees_view.xml